pydgeon/__init__.py
pydgeon/main.py
pydgeon-0.2.4.dist-info/LICENSE.txt
pydgeon-0.2.4.dist-info/METADATA
pydgeon-0.2.4.dist-info/WHEEL
pydgeon-0.2.4.dist-info/top_level.txt
pydgeon-0.2.4.dist-info/RECORD
