Metadata-Version: 2.2
Name: pydgeon
Version: 0.2.4
Summary: A Python library for simplifying sending emails using smtplib
Author-email: GeeseCanHonk <GeeseCanHonk@gmail.com>
License: MIT
Project-URL: Homepage, https://pypi.org/project/pydgeon/
Project-URL: Repository, https://github.com/GeeseCanHonk/pydgeon
Project-URL: Issues, https://github.com/GeeseCanHonk/pydgeon/issues
Requires-Python: >=3.7
License-File: LICENSE.txt
